alfeios/__init__.py
alfeios/api.py
alfeios/cli.py
alfeios/listing.py
alfeios/serialize.py
alfeios/tool.py
alfeios/walker.py
alfeios-1.4.dist-info/LICENSE.txt
alfeios-1.4.dist-info/METADATA
alfeios-1.4.dist-info/WHEEL
alfeios-1.4.dist-info/entry_points.txt
alfeios-1.4.dist-info/top_level.txt
alfeios-1.4.dist-info/RECORD
