Metadata-Version: 2.1
Name: alfeios
Version: 1.4
Summary: Enrich your command-line shell with Herculean cleaning capabilities
Home-page: https://github.com/hoduche/alfeios
Author: Henri-Olivier Duché
Author-email: hoduche@yahoo.fr
License: MIT
Keywords: fs filesystem file system walk crawl files duplicate missing content hash hashcode checksum zip
Classifier: Programming Language :: Python :: 3
Classifier: License :: OSI Approved :: MIT License
Classifier: Operating System :: OS Independent
Requires-Python: >=3.9
License-File: LICENSE.txt
Requires-Dist: colorama
Requires-Dist: dsargparse
Requires-Dist: pytest
Requires-Dist: tqdm
Requires-Dist: flake8
Requires-Dist: pillow
Requires-Dist: pdfkit
Requires-Dist: pypdf
Requires-Dist: mock
